{
    "index": {
        "method" : "get",
        "path" : "/Demo-MVC/public/",
        "controller" : "AppController",
        "action" : "show"  
    },

    "roles": {
        "method" : "get",
        "path" : "/Demo-MVC/public/roles",
        "controller" : "RolesController",
        "action" : "roles"  
    },

    "roles_delete": {
        "method" : "get",
        "path" : "/Demo-MVC/public/roles/delete/([\\d]{1,3})",
        "controller" : "RolesController",
        "action" : "delete"  
    }
}